Metadata-Version: 2.1
Name: edeklaracje-client
Version: 0.0.1
Summary: Library to simplify building Plotly Dash applications
Home-page: https://github.com/rtshadow/simple-dash
Author: Przemyslaw Pastuszka
Author-email: pastuszka.przemyslaw@gmail.com
License: MIT
Platform: UNKNOWN
Requires-Python: >=3.5
